enstat/__init__.py
enstat/_version.py
enstat/detail.py
enstat/mean.py
enstat-0.9.7.dist-info/LICENSE
enstat-0.9.7.dist-info/METADATA
enstat-0.9.7.dist-info/WHEEL
enstat-0.9.7.dist-info/top_level.txt
enstat-0.9.7.dist-info/RECORD
