Metadata-Version: 2.1
Name: enstat
Version: 0.9.7
Summary: Ensemble averages
Author-email: Tom de Geus <tom@geus.me>
Project-URL: Source, https://github.com/tdegeus/enstat
Classifier: License :: OSI Approved :: MIT License
Requires-Python: >=3.6
License-File: LICENSE
Requires-Dist: numpy
